alibabacloud_tdsr20200101/__init__.py
alibabacloud_tdsr20200101/client.py
alibabacloud_tdsr20200101/models/__init__.py
alibabacloud_tdsr20200101/models/_add_hotspot_file_request.py
alibabacloud_tdsr20200101/models/_add_hotspot_file_response.py
alibabacloud_tdsr20200101/models/_add_hotspot_file_response_body.py
alibabacloud_tdsr20200101/models/_add_mosaics_request.py
alibabacloud_tdsr20200101/models/_add_mosaics_response.py
alibabacloud_tdsr20200101/models/_add_mosaics_response_body.py
alibabacloud_tdsr20200101/models/_add_project_request.py
alibabacloud_tdsr20200101/models/_add_project_response.py
alibabacloud_tdsr20200101/models/_add_project_response_body.py
alibabacloud_tdsr20200101/models/_add_relative_position_request.py
alibabacloud_tdsr20200101/models/_add_relative_position_response.py
alibabacloud_tdsr20200101/models/_add_relative_position_response_body.py
alibabacloud_tdsr20200101/models/_add_room_plan_request.py
alibabacloud_tdsr20200101/models/_add_room_plan_response.py
alibabacloud_tdsr20200101/models/_add_room_plan_response_body.py
alibabacloud_tdsr20200101/models/_add_scene_request.py
alibabacloud_tdsr20200101/models/_add_scene_response.py
alibabacloud_tdsr20200101/models/_add_scene_response_body.py
alibabacloud_tdsr20200101/models/_add_sub_scene_request.py
alibabacloud_tdsr20200101/models/_add_sub_scene_response.py
alibabacloud_tdsr20200101/models/_add_sub_scene_response_body.py
alibabacloud_tdsr20200101/models/_check_user_property_request.py
alibabacloud_tdsr20200101/models/_check_user_property_response.py
alibabacloud_tdsr20200101/models/_check_user_property_response_body.py
alibabacloud_tdsr20200101/models/_copy_scene_request.py
alibabacloud_tdsr20200101/models/_copy_scene_response.py
alibabacloud_tdsr20200101/models/_copy_scene_response_body.py
alibabacloud_tdsr20200101/models/_create_upload_policy_request.py
alibabacloud_tdsr20200101/models/_create_upload_policy_response.py
alibabacloud_tdsr20200101/models/_create_upload_policy_response_body.py
alibabacloud_tdsr20200101-3.1.8.dist-info/LICENSE
alibabacloud_tdsr20200101-3.1.8.dist-info/METADATA
alibabacloud_tdsr20200101-3.1.8.dist-info/WHEEL
alibabacloud_tdsr20200101-3.1.8.dist-info/top_level.txt
alibabacloud_tdsr20200101-3.1.8.dist-info/RECORD
